{"assets/Desgin/1.png":["assets/Desgin/1.png"],"assets/Desgin/deadpool2.png":["assets/Desgin/deadpool2.png"],"assets/Desgin/meliods0.1.jpg":["assets/Desgin/meliods0.1.jpg"],"assets/Desgin/nega%20girl.png":["assets/Desgin/nega%20girl.png"],"assets/Desgin/queen1.png":["assets/Desgin/queen1.png"],"assets/Desgin/somebody.png":["assets/Desgin/somebody.png"],"assets/Desgin/ziad.jpg":["assets/Desgin/ziad.jpg"],"assets/Fonts/Age.otf":["assets/Fonts/Age.otf"],"assets/Fonts/Mulish-Black.ttf":["assets/Fonts/Mulish-Black.ttf"],"assets/Fonts/Mulish-Light.ttf":["assets/Fonts/Mulish-Light.ttf"],"assets/Fonts/Poppins-Black.ttf":["assets/Fonts/Poppins-Black.ttf"],"assets/Fonts/Poppins-Italic.ttf":["assets/Fonts/Poppins-Italic.ttf"],"assets/Fonts/Poppins-SemiBold.ttf":["assets/Fonts/Poppins-SemiBold.ttf"],"assets/Loadinglogo/ezgif.com-gif-maker.gif":["assets/Loadinglogo/ezgif.com-gif-maker.gif"],"assets/Svg/avatar.svg":["assets/Svg/avatar.svg"],"assets/Svg/briefcase.svg":["assets/Svg/briefcase.svg"],"assets/Svg/home-run.svg":["assets/Svg/home-run.svg"],"assets/Svg/mail.svg":["assets/Svg/mail.svg"],"packages/cupertino_icons/assets/CupertinoIcons.ttf":["packages/cupertino_icons/assets/CupertinoIcons.ttf"]}